pensando_cloud/__init__.py
pensando_cloud/example.py
pensando_cloud/setup.py
pensando_cloud/psm/__init__.py
pensando_cloud/psm/api_client.py
pensando_cloud/psm/configuration.py
pensando_cloud/psm/exceptions.py
pensando_cloud/psm/login.py
pensando_cloud/psm/model_utils.py
pensando_cloud/psm/rest.py
pensando_cloud/psm/api/__init__.py
pensando_cloud/psm/api/audit_v1_api.py
pensando_cloud/psm/api/auth_v1_api.py
pensando_cloud/psm/api/browser_v1_api.py
pensando_cloud/psm/api/cluster_v1_api.py
pensando_cloud/psm/api/diagnostics_v1_api.py
pensando_cloud/psm/api/events_v1_api.py
pensando_cloud/psm/api/fwlog_v1_api.py
pensando_cloud/psm/api/monitoring_v1_api.py
pensando_cloud/psm/api/network_v1_api.py
pensando_cloud/psm/api/objstore_v1_api.py
pensando_cloud/psm/api/orchestration_v1_api.py
pensando_cloud/psm/api/rollout_v1_api.py
pensando_cloud/psm/api/routing_v1_api.py
pensando_cloud/psm/api/search_v1_api.py
pensando_cloud/psm/api/security_v1_api.py
pensando_cloud/psm/api/staging_v1_api.py
pensando_cloud/psm/api/telemetry_query_v1_api.py
pensando_cloud/psm/api/tokenauth_v1_api.py
pensando_cloud/psm/api/workload_v1_api.py
pensando_cloud/psm/apis/__init__.py
pensando_cloud/psm/apis/aggwatch/__init__.py
pensando_cloud/psm/apis/audit/__init__.py
pensando_cloud/psm/apis/auth/__init__.py
pensando_cloud/psm/apis/browser/__init__.py
pensando_cloud/psm/apis/cluster/__init__.py
pensando_cloud/psm/apis/diagnostics/__init__.py
pensando_cloud/psm/apis/events/__init__.py
pensando_cloud/psm/apis/fwlog/__init__.py
pensando_cloud/psm/apis/monitoring/__init__.py
pensando_cloud/psm/apis/network/__init__.py
pensando_cloud/psm/apis/objstore/__init__.py
pensando_cloud/psm/apis/orchestration/__init__.py
pensando_cloud/psm/apis/rollout/__init__.py
pensando_cloud/psm/apis/routing/__init__.py
pensando_cloud/psm/apis/search/__init__.py
pensando_cloud/psm/apis/security/__init__.py
pensando_cloud/psm/apis/staging/__init__.py
pensando_cloud/psm/apis/telemetry_query/__init__.py
pensando_cloud-1.16.3.dist-info/METADATA
pensando_cloud-1.16.3.dist-info/WHEEL
pensando_cloud-1.16.3.dist-info/top_level.txt
pensando_cloud-1.16.3.dist-info/RECORD
