Metadata-Version: 2.1
Name: pensando-cloud
Version: 1.16.3
Summary: Python language bindings for Pensando cloud
Home-page: https://github.com/pensando/pypi
Author: Jeff Silberman
Author-email: jeff@pensando.io
License: UNKNOWN
Project-URL: Bug Tracker, https://github.com/pensando/psm-tools/issues
Platform: UNKNOWN
Classifier: Programming Language :: Python :: 3
Classifier: License :: OSI Approved :: MIT License
Classifier: Operating System :: OS Independent
Requires-Python: >=3.6
Requires-Dist: nulltype
